Metadata-Version: 2.1
Name: SEELE-test
Version: 1.1.3
Summary: Test of pip for SEELE development
Home-page: https://github.com/JMalegni/DisasterPrepApp
Author: Nicholas DeSanctis
Author-email: nickdesanctis17@gmail.com
Project-URL: Source, https://github.com/JMalegni/DisasterPrepApp
Classifier: Development Status :: 3 - Alpha
Classifier: Framework :: Django
Classifier: Programming Language :: Python :: 3
Classifier: Programming Language :: Python :: 3.8
License-File: LICENSE
Requires-Dist: django (>=5.0.6)
Requires-Dist: django-bootstrap4 (>=23.4)
Requires-Dist: sqlparse (>=0.3.1)
